csgimu/__init__.py
csgimu/cpp/__init__.py
csgimu/cpp/dummy.cpython-38-i386-linux-gnu.so
csgimu/cpp/dummy.cpp
csgimu/cpp/dummy_src/dummy.cpp
csgimu/matlab/+csgimu/matlabDummy.m
csgimu/functions/__init__.py
csgimu/functions/dummy.py
csgimu-0.0.2.dist-info/WHEEL
csgimu-0.0.2.dist-info/top_level.txt
csgimu-0.0.2.dist-info/RECORD
csgimu-0.0.2.dist-info/METADATA
