Metadata-Version: 2.1
Name: csgimu
Version: 0.0.2
Summary: This is a dummy repo for testing. Real code coming soon.
Home-page: https://github.com/dlaidig/csgimu/
Author: Daniel Laidig
Author-email: laidig@control.tu-berlin.de
License: MIT
Project-URL: Documentation, https://csgimu.readthedocs.io/
Platform: UNKNOWN
Classifier: Development Status :: 3 - Alpha
Classifier: Intended Audience :: Science/Research
Classifier: License :: OSI Approved :: MIT License
Classifier: Programming Language :: Python :: 3
Requires-Dist: numpy
Requires-Dist: scipy
Requires-Dist: matplotlib
Requires-Dist: PyYAML
Requires-Dist: transplant (>=0.8.11)
Requires-Dist: aiohttp
Requires-Dist: ipython
Requires-Dist: notebook
Requires-Dist: aiofiles
Requires-Dist: orjson
Provides-Extra: dev
Requires-Dist: pytest ; extra == 'dev'
Requires-Dist: pytest-flake8 ; extra == 'dev'
Requires-Dist: reuse ; extra == 'dev'
Requires-Dist: Cython ; extra == 'dev'
Requires-Dist: sphinx ; extra == 'dev'
Requires-Dist: recommonmark ; extra == 'dev'
Requires-Dist: sphinx-rtd-theme ; extra == 'dev'
Requires-Dist: sphinxcontrib-matlabdomain ; extra == 'dev'
